splitflow/__init__.py
splitflow/dataframe.py
splitflow-0.0.5.dist-info/LICENSE.txt
splitflow-0.0.5.dist-info/METADATA
splitflow-0.0.5.dist-info/WHEEL
splitflow-0.0.5.dist-info/top_level.txt
splitflow-0.0.5.dist-info/RECORD
